mext/__init__.py
mext/enums.py
mext/exceptions.py
mext/provider.py
mext/utils.py
mext/bases/__init__.py
mext/bases/b_madara_wp.py
mext/bases/b_mangastream_wp.py
mext/client/__init__.py
mext/client/http/__init__.py
mext/client/selenium/__init__.py
mext/client/selenium/chrome.py
mext/client/selenium/firefox.py
mext/client/selenium/web_driver.py
mext/models/__init__.py
mext/models/chapter.py
mext/models/cover.py
mext/models/genre.py
mext/models/group.py
mext/models/link.py
mext/models/manga.py
mext/models/model.py
mext/models/page.py
mext/models/person.py
mext/models/tag.py
mext/providers/__init__.py
mext/providers/p_asurascans_com.py
mext/providers/p_flamescans_org.py
mext/providers/p_mangadex_org.py
mext/providers/p_mangaupdates_com.py
mext/providers/p_manhuaplus_com.py
mext/providers/p_reaperscans_com.py
tests/__init__.py
tests/asurascans.py
tests/mangadex.py
mext-2.0.10.dist-info/LICENSE
mext-2.0.10.dist-info/METADATA
mext-2.0.10.dist-info/WHEEL
mext-2.0.10.dist-info/top_level.txt
mext-2.0.10.dist-info/RECORD
