Metadata-Version: 2.1
Name: mext
Version: 2.0.10
Summary: A simple manga extractor. Extracts any comic info, chapter list and chapter pages. In development.
Home-page: https://github.com/modbender/manga-extractor
Author: Yashas H R
Author-email: rameshmamathayashas@gmail.com
Platform: any
Classifier: License :: OSI Approved :: BSD License
Classifier: Natural Language :: English
Classifier: Environment :: Console
Classifier: Programming Language :: Python :: 3
Classifier: Programming Language :: Python :: 3 :: Only
Classifier: Topic :: Internet :: WWW/HTTP
Requires-Python: >=3.5
License-File: LICENSE
Requires-Dist: requests
Requires-Dist: lxml (>=4.6.0)
Requires-Dist: cloudscraper
Requires-Dist: beautifulsoup4 (>=4.10.0)
